pyThingPark/__init__.py
pyThingPark/device.py
pyThingPark/dxMaker.py
pyThingPark/lorawan.py
pyThingPark/uplinkTunnel.py
pyThingPark-0.0.4.dist-info/LICENSE.txt
pyThingPark-0.0.4.dist-info/METADATA
pyThingPark-0.0.4.dist-info/WHEEL
pyThingPark-0.0.4.dist-info/top_level.txt
pyThingPark-0.0.4.dist-info/RECORD
