Metadata-Version: 2.1
Name: pyThingPark
Version: 0.0.4
Summary: Python tools for ThingPark
Home-page: https://github.com/actility/pyThingPark
Author: Raphael Apfeldorfer
Author-email: raphael.apfeldorfer@actility.com
License: UNKNOWN
Platform: UNKNOWN
Classifier: Programming Language :: Python :: 3
Classifier: License :: OSI Approved :: BSD License
Classifier: Operating System :: OS Independent
Classifier: Development Status :: 4 - Beta
Requires-Python: >=3.6
Requires-Dist: cryptography
